afs/__init__.py
afs/afs_local.py
afs/afs_memory.py
afs/afs_sftp.py
afs/afs_smb.py
afs/core.py
afs/errors.py
afs/exceptions.py
afs/log.py
agnostic_file_store-0.5.4.dist-info/LICENSE.txt
agnostic_file_store-0.5.4.dist-info/METADATA
agnostic_file_store-0.5.4.dist-info/WHEEL
agnostic_file_store-0.5.4.dist-info/top_level.txt
agnostic_file_store-0.5.4.dist-info/RECORD
