Metadata-Version: 2.1
Name: agnostic-file-store
Version: 0.5.4
Summary: An agnostic, easy-to-use module for different file systems (Memory | local | Samba (SMB) | NFS | Amazon S3)
Home-page: https://github.com/euribates/agnostic-file-store/
Author: Juan Ignacio Rodríguez de León
Author-email: euribates@gmail.com
License: UNKNOWN
Download-URL: https://github.com/euribates/agnostic-file-store/archive/master.zip
Project-URL: source, https://github.com/euribates/agnostic-file-store/
Project-URL: download, https://github.com/euribates/agnostic-file-store/archive/master.zip
Keywords: agnostic,AMS,CIFS,NAS,S3,Samba,SAN,SMB,storage
Platform: UNKNOWN
Classifier: Development Status :: 4 - Beta
Classifier: Intended Audience :: Developers
Classifier: Programming Language :: Python :: 2.7
Classifier: Programming Language :: Python :: 3
Classifier: Programming Language :: Python :: 3.3
Classifier: Programming Language :: Python :: 3.4
Classifier: Programming Language :: Python :: 3.5
Classifier: Programming Language :: Python :: 3.6
Classifier: Programming Language :: Python :: 3.7
Classifier: Programming Language :: Python :: 3.8
Classifier: Programming Language :: Python :: 3.9
Classifier: License :: OSI Approved :: GNU General Public License v3 or later (GPLv3+)
Classifier: Topic :: Software Development :: Libraries
License-File: LICENSE.txt
Requires-Dist: pysmb
